{"Year":[2000,2004,2005,2009,2010,2011,2012,2013,2014,2015,2016,2017,2018,2020,2009,2010,2011,2012,2013,2014,2015,2016,2017,2018,2020,2007,2008,2009,2011,2012,2013,2014,2015,2016,2017,2018,2019,2020,2004,2009,2010,2012,2013,2014,2015,2016,2017,2018,2020,2012,2015,2018,2012,2015,2017,2018,2012,2015,2018,2012,2015,2017,2018],"SERIES":["SH_MED_DEN","SH_MED_DEN","SH_MED_DEN","SH_MED_DEN","SH_MED_DEN","SH_MED_DEN","SH_MED_DEN","SH_MED_DEN","SH_MED_DEN","SH_MED_DEN","SH_MED_DEN","SH_MED_DEN","SH_MED_DEN","SH_MED_DEN","SH_MED_DEN","SH_MED_DEN","SH_MED_DEN","SH_MED_DEN","SH_MED_DEN","SH_MED_DEN","SH_MED_DEN","SH_MED_DEN","SH_MED_DEN","SH_MED_DEN","SH_MED_DEN","SH_MED_DEN","SH_MED_DEN","SH_MED_DEN","SH_MED_DEN","SH_MED_DEN","SH_MED_DEN","SH_MED_DEN","SH_MED_DEN","SH_MED_DEN","SH_MED_DEN","SH_MED_DEN","SH_MED_DEN","SH_MED_DEN","SH_MED_DEN","SH_MED_DEN","SH_MED_DEN","SH_MED_DEN","SH_MED_DEN","SH_MED_DEN","SH_MED_DEN","SH_MED_DEN","SH_MED_DEN","SH_MED_DEN","SH_MED_DEN","SH_MED_HWRKDIS","SH_MED_HWRKDIS","SH_MED_HWRKDIS","SH_MED_HWRKDIS","SH_MED_HWRKDIS","SH_MED_HWRKDIS","SH_MED_HWRKDIS","SH_MED_HWRKDIS","SH_MED_HWRKDIS","SH_MED_HWRKDIS","SH_MED_HWRKDIS","SH_MED_HWRKDIS","SH_MED_HWRKDIS","SH_MED_HWRKDIS"],"SEX":[null,null,null,null,null,null,null,null,null,null,null,null,null,null,null,null,null,null,null,null,null,null,null,null,null,null,null,null,null,null,null,null,null,null,null,null,null,null,null,null,null,null,null,null,null,null,null,null,null,"F","F","F","F","F","F","F","M","M","M","M","M","M","M"],"OCCUPATION":["ISCO08_221","ISCO08_221","ISCO08_221","ISCO08_221","ISCO08_221","ISCO08_221","ISCO08_221","ISCO08_221","ISCO08_221","ISCO08_221","ISCO08_221","ISCO08_221","ISCO08_221","ISCO08_221","ISCO08_222_322","ISCO08_222_322","ISCO08_222_322","ISCO08_222_322","ISCO08_222_322","ISCO08_222_322","ISCO08_222_322","ISCO08_222_322","ISCO08_222_322","ISCO08_222_322","ISCO08_222_322","ISCO08_2261","ISCO08_2261","ISCO08_2261","ISCO08_2261","ISCO08_2261","ISCO08_2261","ISCO08_2261","ISCO08_2261","ISCO08_2261","ISCO08_2261","ISCO08_2261","ISCO08_2261","ISCO08_2261","ISCO08_2262","ISCO08_2262","ISCO08_2262","ISCO08_2262","ISCO08_2262","ISCO08_2262","ISCO08_2262","ISCO08_2262","ISCO08_2262","ISCO08_2262","ISCO08_2262","ISCO08_221","ISCO08_221","ISCO08_221","ISCO08_2221_3221","ISCO08_2221_3221","ISCO08_2221_3221","ISCO08_2221_3221","ISCO08_221","ISCO08_221","ISCO08_221","ISCO08_2221_3221","ISCO08_2221_3221","ISCO08_2221_3221","ISCO08_2221_3221"],"UNIT_MEASURE":["PER_10000_POP","PER_10000_POP","PER_10000_POP","PER_10000_POP","PER_10000_POP","PER_10000_POP","PER_10000_POP","PER_10000_POP","PER_10000_POP","PER_10000_POP","PER_10000_POP","PER_10000_POP","PER_10000_POP","PER_10000_POP","PER_10000_POP","PER_10000_POP","PER_10000_POP","PER_10000_POP","PER_10000_POP","PER_10000_POP","PER_10000_POP","PER_10000_POP","PER_10000_POP","PER_10000_POP","PER_10000_POP","PER_10000_POP","PER_10000_POP","PER_10000_POP","PER_10000_POP","PER_10000_POP","PER_10000_POP","PER_10000_POP","PER_10000_POP","PER_10000_POP","PER_10000_POP","PER_10000_POP","PER_10000_POP","PER_10000_POP","PER_10000_POP","PER_10000_POP","PER_10000_POP","PER_10000_POP","PER_10000_POP","PER_10000_POP","PER_10000_POP","PER_10000_POP","PER_10000_POP","PER_10000_POP","PER_10000_POP","PT","PT","PT","PT","PT","PT","PT","PT","PT","PT","PT","PT","PT","PT"],"Value":[1.27,1.72,1.24,1.2,1.26,0.81,0.8,0.82,1.22,1.77,1.74,1.79,2.01,1.89,9.38,8.2,13.07,11.71,13.81,15.07,13.49,13.59,25.07,18.52,20.29,0.15,0.14,0.14,0.2,0.18,0.17,0.08,0.05,0.09,0.07,0.07,0.16,0.15,0.5,0.54,0.04,0.29,0.29,0.14,0.1,0.15,0.18,0.93,1.02,32.5,37.0,28.2,79.2,61.9,77.3,76.0,67.5,63.0,71.8,20.8,38.1,22.7,24.0]}